{
    "call_sign": "Disaster_City_Survey",
    "position": {
        "latitude": 30.574282795745027,
        "longitude": -96.35265313400068,
        "altitude": 127.67
    },
    "velocity": {
        "airspeed": 17.39,
        "ground_speed": 17.39,
        "verticle_speed": 0.26,
        "units_speed": "MetersPerSecond",
        "track": 161.84
    },
    "time_measured": "2025-01-27T12:08:43Z",
    "battery": {
        "voltage": 11.44,
        "current": 5.3
    },
    "orientation": {
        "pitch": 1.8,
        "roll": -0.3,
        "yaw": 147.1,
        "pitch_rate": -0.66,
        "roll_rate": 0.25,
        "yaw_rate": 0.42
    },
    "airframe": "Quadcopter"
}